SankeyExcelParser/__init__.py
SankeyExcelParser/io_excel.py
SankeyExcelParser/io_excel_constants.py
SankeyExcelParser/sankey.py
SankeyExcelParser/su_trace.py
SankeyExcelParser/sankey_utils/__init__.py
SankeyExcelParser/sankey_utils/data.py
SankeyExcelParser/sankey_utils/excel_source.py
SankeyExcelParser/sankey_utils/flux.py
SankeyExcelParser/sankey_utils/functions.py
SankeyExcelParser/sankey_utils/node.py
SankeyExcelParser/sankey_utils/sankey_object.py
SankeyExcelParser/sankey_utils/table_object.py
SankeyExcelParser/sankey_utils/tag.py
SankeyExcelParser/sankey_utils/tag_group.py
SankeyExcelParser/sankey_utils/protos/__init__.py
SankeyExcelParser/sankey_utils/protos/flux.py
SankeyExcelParser/sankey_utils/protos/node.py
SankeyExcelParser/sankey_utils/protos/sankey_object.py
SankeyExcelParser/sankey_utils/protos/tag_group.py
SankeyExcelParser/tests/integration/__init__.py
SankeyExcelParser/tests/integration/test_base.py
SankeyExcelParser/tests/integration/test_run_check_input.py
SankeyExcelParser/tests/integration/test_run_conversions.py
SankeyExcelParser/tests/integration/test_run_load_input.py
SankeyExcelParser/tests/unit/__init__.py
SankeyExcelParser-1.0.0b1.data/scripts/run_parse_and_write_excel.py
SankeyExcelParser-1.0.0b1.data/scripts/run_parse_excel.py
SankeyExcelParser-1.0.0b1.dist-info/LICENSE
SankeyExcelParser-1.0.0b1.dist-info/METADATA
SankeyExcelParser-1.0.0b1.dist-info/WHEEL
SankeyExcelParser-1.0.0b1.dist-info/top_level.txt
SankeyExcelParser-1.0.0b1.dist-info/RECORD
