Metadata-Version: 2.1
Name: SankeyExcelParser
Version: 1.0.0b1
Summary: Excel Parser for OpenSankey suite
Home-page: https://gitlab.com/terriflux-public/sankeyexcelparser
Author: TerriFlux
Author-email: julien.alapetite@terriflux.fr
License-File: LICENSE
Requires-Dist: openpyxl
Requires-Dist: pandas
Requires-Dist: argparse
Requires-Dist: xmltodict
Requires-Dist: psutil
Requires-Dist: xlrd
Requires-Dist: numpy
Requires-Dist: seaborn
Requires-Dist: Unidecode
Requires-Dist: xlwings
